kubernetes/__init__.py
kubernetes/client/__init__.py
kubernetes/client/api_client.py
kubernetes/client/configuration.py
kubernetes/client/exceptions.py
kubernetes/client/rest.py
kubernetes/client/api/__init__.py
kubernetes/client/api/admissionregistration_api.py
kubernetes/client/api/admissionregistration_v1_api.py
kubernetes/client/api/admissionregistration_v1alpha1_api.py
kubernetes/client/api/admissionregistration_v1beta1_api.py
kubernetes/client/api/apiextensions_api.py
kubernetes/client/api/apiextensions_v1_api.py
kubernetes/client/api/apiregistration_api.py
kubernetes/client/api/apiregistration_v1_api.py
kubernetes/client/api/apis_api.py
kubernetes/client/api/apps_api.py
kubernetes/client/api/apps_v1_api.py
kubernetes/client/api/authentication_api.py
kubernetes/client/api/authentication_v1_api.py
kubernetes/client/api/authentication_v1alpha1_api.py
kubernetes/client/api/authentication_v1beta1_api.py
kubernetes/client/api/authorization_api.py
kubernetes/client/api/authorization_v1_api.py
kubernetes/client/api/autoscaling_api.py
kubernetes/client/api/autoscaling_v1_api.py
kubernetes/client/api/autoscaling_v2_api.py
kubernetes/client/api/batch_api.py
kubernetes/client/api/batch_v1_api.py
kubernetes/client/api/certificates_api.py
kubernetes/client/api/certificates_v1_api.py
kubernetes/client/api/certificates_v1alpha1_api.py
kubernetes/client/api/coordination_api.py
kubernetes/client/api/coordination_v1_api.py
kubernetes/client/api/core_api.py
kubernetes/client/api/core_v1_api.py
kubernetes/client/api/custom_objects_api.py
kubernetes/client/api/discovery_api.py
kubernetes/client/api/discovery_v1_api.py
kubernetes/client/api/events_api.py
kubernetes/client/api/events_v1_api.py
kubernetes/client/api/flowcontrol_apiserver_api.py
kubernetes/client/api/flowcontrol_apiserver_v1_api.py
kubernetes/client/api/flowcontrol_apiserver_v1beta3_api.py
kubernetes/client/api/internal_apiserver_api.py
kubernetes/client/api/internal_apiserver_v1alpha1_api.py
kubernetes-30.1.0.dist-info/LICENSE
kubernetes-30.1.0.dist-info/METADATA
kubernetes-30.1.0.dist-info/WHEEL
kubernetes-30.1.0.dist-info/top_level.txt
kubernetes-30.1.0.dist-info/RECORD
